adktools/__init__.py
adktools/decorators.py
adktools/discovery.py
adktools/models.py
adktools/responses.py
adktools-0.1.0.dist-info/licenses/LICENSE.md
adktools-0.1.0.dist-info/METADATA
adktools-0.1.0.dist-info/WHEEL
adktools-0.1.0.dist-info/top_level.txt
adktools-0.1.0.dist-info/RECORD
