Metadata-Version: 2.4
Name: adktools
Version: 0.1.0
Summary: Utilities for building Agent Development Kit (ADK) applications
Author-email: chris hay <chrishayuk@example.com>
License: MIT
Project-URL: Homepage, https://github.com/chrishayuk/adktools
Project-URL: Bug Tracker, https://github.com/chrishayuk/adktools/issues
Keywords: adk,google,agent,tools,ai
Classifier: Development Status :: 4 - Beta
Classifier: Intended Audience :: Developers
Classifier: License :: OSI Approved :: MIT License
Classifier: Programming Language :: Python :: 3
Classifier: Programming Language :: Python :: 3.9
Classifier: Programming Language :: Python :: 3.10
Classifier: Programming Language :: Python :: 3.11
Classifier: Programming Language :: Python :: 3.12
Requires-Python: >=3.9
License-File: LICENSE.md
Requires-Dist: pydantic>=2.0.0
Dynamic: license-file
